text2kwl
kasahorow
pronounce
kwl
voice
data
kwl2text
