Metadata-Version: 1.0
Name: kwl
Version: 0.2016.6.0
Summary: Utilities for KWL: kasahorow Writer's Language
Home-page: https://www.kasahorow.org/
Author: Paa Kwesi Imbeah
Author-email: imbeah@yahoo.com
License: BSD
Keywords: translation kasahorow
Platform: UNKNOWN
